satelles/__init__.py
satelles/body.py
satelles/checksum.py
satelles/common.py
satelles/constants.py
satelles/coordinates.py
satelles/covariance.py
satelles/differentiation.py
satelles/earth.py
satelles/frame.py
satelles/frames.py
satelles/gravity.py
satelles/hohmann.py
satelles/interpolation.py
satelles/kepler.py
satelles/matrix.py
satelles/mjd.py
satelles/models.py
satelles/orbit.py
satelles/origin.py
satelles/py.typed
satelles/quaternion.py
satelles/runge_kutta.py
satelles/satellite.py
satelles/symplectic.py
satelles/tle.py
satelles/transforms.py
satelles/vector.py
satelles/velocity.py
satelles/visibility.py
satelles-0.28.0.dist-info/METADATA
satelles-0.28.0.dist-info/WHEEL
satelles-0.28.0.dist-info/licenses/LICENSE
satelles-0.28.0.dist-info/RECORD
