Metadata-Version: 2.4
Name: satelles
Version: 0.28.0
Summary: Modern, type-safe python library for TLE, OMM et al. handling and orbit propagation to accurately locate your satellites in the sky.
Author-email: michealroberts <michael@observerly.com>
License: MIT License
License-File: LICENSE
Keywords: astrodynamics,astronomy,omm,orbit,propagation,satellite,tle
Classifier: Development Status :: 3 - Alpha
Classifier: Intended Audience :: Developers
Classifier: License :: OSI Approved :: MIT License
Classifier: Programming Language :: Python :: 3
Classifier: Programming Language :: Python :: 3 :: Only
Classifier: Programming Language :: Python :: 3.11
Classifier: Programming Language :: Python :: 3.12
Classifier: Programming Language :: Python :: 3.13
Classifier: Programming Language :: Python :: 3.14
Classifier: Typing :: Typed
Requires-Python: >=3.11
Requires-Dist: celerity>=0.41.0
Requires-Dist: pydantic>=2.12.4
